{
  "json_format_version": [
    1,
    0
  ],
  "smartctl": {
    "version": [
      7,
      1
    ],
    "svn_revision": "5022",
    "platform_info": "x86_64-linux-5.9.1-2-default",
    "build_info": "(SUSE RPM)",
    "argv": [
      "smartctl",
      "--all",
      "--json",
      "/dev/sdb"
    ],
    "exit_status": 192
  },
  "device": {
    "name": "/dev/sdb",
    "info_name": "/dev/sdb [SAT]",
    "type": "sat",
    "protocol": "ATA"
  },
  "model_family": "Seagate Barracuda 7200.14 (AF)",
  "model_name": "ST3000DM001-1ER166",
  "serial_number": "Z501MAQ5",
  "wwn": {
    "naa": 5,
    "oui": 3152,
    "id": 2077688006
  },
  "firmware_version": "CC26",
  "user_capacity": {
    "blocks": 5860533168,
    "bytes": 3000592982016
  },
  "logical_block_size": 512,
  "physical_block_size": 4096,
  "rotation_rate": 7200,
  "form_factor": {
    "ata_value": 2,
    "name": "3.5 inches"
  },
  "in_smartctl_database": true,
  "ata_version": {
    "string": "ACS-2, ACS-3 T13/2161-D revision 3b",
    "major_value": 1008,
    "minor_value": 31
  },
  "sata_version": {
    "string": "SATA 3.1",
    "value": 126
  },
  "interface_speed": {
    "max": {
      "sata_value": 14,
      "string": "6.0 Gb/s",
      "units_per_second": 60,
      "bits_per_unit": 100000000
    },
    "current": {
      "sata_value": 3,
      "string": "6.0 Gb/s",
      "units_per_second": 60,
      "bits_per_unit": 100000000
    }
  },
  "local_time": {
    "time_t": 1605791867,
    "asctime": "Thu Nov 19 10:17:47 2020 -03"
  },
  "smart_status": {
    "passed": true
  },
  "ata_smart_data": {
    "offline_data_collection": {
      "status": {
        "value": 0,
        "string": "was never started"
      },
      "completion_seconds": 89
    },
    "self_test": {
      "status": {
        "value": 0,
        "string": "completed without error",
        "passed": true
      },
      "polling_minutes": {
        "short": 1,
        "extended": 321,
        "conveyance": 2
      }
    },
    "capabilities": {
      "values": [
        115,
        3
      ],
      "exec_offline_immediate_supported": true,
      "offline_is_aborted_upon_new_cmd": false,
      "offline_surface_scan_supported": false,
      "self_tests_supported": true,
      "conveyance_self_test_supported": true,
      "selective_self_test_supported": true,
      "attribute_autosave_enabled": true,
      "error_logging_supported": true,
      "gp_logging_supported": true
    }
  },
  "ata_sct_capabilities": {
    "value": 4229,
    "error_recovery_control_supported": false,
    "feature_control_supported": false,
    "data_table_supported": false
  },
  "ata_smart_attributes": {
    "revision": 10,
    "table": [
      {
        "id": 1,
        "name": "Raw_Read_Error_Rate",
        "value": 119,
        "worst": 99,
        "thresh": 6,
        "when_failed": "",
        "flags": {
          "value": 15,
          "string": "POSR-- ",
          "prefailure": true,
          "updated_online": true,
          "performance": true,
          "error_rate": true,
          "event_count": false,
          "auto_keep": false
        },
        "raw": {
          "value": 220698288,
          "string": "220698288"
        }
      },
      {
        "id": 3,
        "name": "Spin_Up_Time",
        "value": 95,
        "worst": 94,
        "thresh": 0,
        "when_failed": "",
        "flags": {
          "value": 3,
          "string": "PO---- ",
          "prefailure": true,
          "updated_online": true,
          "performance": false,
          "error_rate": false,
          "event_count": false,
          "auto_keep": false
        },
        "raw": {
          "value": 0,
          "string": "0"
        }
      },
      {
        "id": 4,
        "name": "Start_Stop_Count",
        "value": 100,
        "worst": 100,
        "thresh": 20,
        "when_failed": "",
        "flags": {
          "value": 50,
          "string": "-O--CK ",
          "prefailure": false,
          "updated_online": true,
          "performance": false,
          "error_rate": false,
          "event_count": true,
          "auto_keep": true
        },
        "raw": {
          "value": 474,
          "string": "474"
        }
      },
      {
        "id": 5,
        "name": "Reallocated_Sector_Ct",
        "value": 100,
        "worst": 100,
        "thresh": 10,
        "when_failed": "",
        "flags": {
          "value": 51,
          "string": "PO--CK ",
          "prefailure": true,
          "updated_online": true,
          "performance": false,
          "error_rate": false,
          "event_count": true,
          "auto_keep": true
        },
        "raw": {
          "value": 8,
          "string": "8"
        }
      },
      {
        "id": 7,
        "name": "Seek_Error_Rate",
        "value": 70,
        "worst": 47,
        "thresh": 30,
        "when_failed": "",
        "flags": {
          "value": 15,
          "string": "POSR-- ",
          "prefailure": true,
          "updated_online": true,
          "performance": true,
          "error_rate": true,
          "event_count": false,
          "auto_keep": false
        },
        "raw": {
          "value": 387418648463,
          "string": "387418648463"
        }
      },
      {
        "id": 9,
        "name": "Power_On_Hours",
        "value": 69,
        "worst": 69,
        "thresh": 0,
        "when_failed": "",
        "flags": {
          "value": 50,
          "string": "-O--CK ",
          "prefailure": false,
          "updated_online": true,
          "performance": false,
          "error_rate": false,
          "event_count": true,
          "auto_keep": true
        },
        "raw": {
          "value": 27205,
          "string": "27205"
        }
      },
      {
        "id": 10,
        "name": "Spin_Retry_Count",
        "value": 100,
        "worst": 100,
        "thresh": 97,
        "when_failed": "",
        "flags": {
          "value": 19,
          "string": "PO--C- ",
          "prefailure": true,
          "updated_online": true,
          "performance": false,
          "error_rate": false,
          "event_count": true,
          "auto_keep": false
        },
        "raw": {
          "value": 0,
          "string": "0"
        }
      },
      {
        "id": 12,
        "name": "Power_Cycle_Count",
        "value": 100,
        "worst": 100,
        "thresh": 20,
        "when_failed": "",
        "flags": {
          "value": 50,
          "string": "-O--CK ",
          "prefailure": false,
          "updated_online": true,
          "performance": false,
          "error_rate": false,
          "event_count": true,
          "auto_keep": true
        },
        "raw": {
          "value": 405,
          "string": "405"
        }
      },
      {
        "id": 183,
        "name": "Runtime_Bad_Block",
        "value": 99,
        "worst": 99,
        "thresh": 0,
        "when_failed": "",
        "flags": {
          "value": 50,
          "string": "-O--CK ",
          "prefailure": false,
          "updated_online": true,
          "performance": false,
          "error_rate": false,
          "event_count": true,
          "auto_keep": true
        },
        "raw": {
          "value": 1,
          "string": "1"
        }
      },
      {
        "id": 184,
        "name": "End-to-End_Error",
        "value": 100,
        "worst": 100,
        "thresh": 99,
        "when_failed": "",
        "flags": {
          "value": 50,
          "string": "-O--CK ",
          "prefailure": false,
          "updated_online": true,
          "performance": false,
          "error_rate": false,
          "event_count": true,
          "auto_keep": true
        },
        "raw": {
          "value": 0,
          "string": "0"
        }
      },
      {
        "id": 187,
        "name": "Reported_Uncorrect",
        "value": 11,
        "worst": 11,
        "thresh": 0,
        "when_failed": "",
        "flags": {
          "value": 50,
          "string": "-O--CK ",
          "prefailure": false,
          "updated_online": true,
          "performance": false,
          "error_rate": false,
          "event_count": true,
          "auto_keep": true
        },
        "raw": {
          "value": 89,
          "string": "89"
        }
      },
      {
        "id": 188,
        "name": "Command_Timeout",
        "value": 100,
        "worst": 99,
        "thresh": 0,
        "when_failed": "",
        "flags": {
          "value": 50,
          "string": "-O--CK ",
          "prefailure": false,
          "updated_online": true,
          "performance": false,
          "error_rate": false,
          "event_count": true,
          "auto_keep": true
        },
        "raw": {
          "value": 5,
          "string": "0 0 5"
        }
      },
      {
        "id": 189,
        "name": "High_Fly_Writes",
        "value": 82,
        "worst": 82,
        "thresh": 0,
        "when_failed": "",
        "flags": {
          "value": 58,
          "string": "-O-RCK ",
          "prefailure": false,
          "updated_online": true,
          "performance": false,
          "error_rate": true,
          "event_count": true,
          "auto_keep": true
        },
        "raw": {
          "value": 18,
          "string": "18"
        }
      },
      {
        "id": 190,
        "name": "Airflow_Temperature_Cel",
        "value": 63,
        "worst": 52,
        "thresh": 45,
        "when_failed": "",
        "flags": {
          "value": 34,
          "string": "-O---K ",
          "prefailure": false,
          "updated_online": true,
          "performance": false,
          "error_rate": false,
          "event_count": false,
          "auto_keep": true
        },
        "raw": {
          "value": 622657573,
          "string": "37 (Min/Max 29/37)"
        }
      },
      {
        "id": 191,
        "name": "G-Sense_Error_Rate",
        "value": 100,
        "worst": 100,
        "thresh": 0,
        "when_failed": "",
        "flags": {
          "value": 50,
          "string": "-O--CK ",
          "prefailure": false,
          "updated_online": true,
          "performance": false,
          "error_rate": false,
          "event_count": true,
          "auto_keep": true
        },
        "raw": {
          "value": 0,
          "string": "0"
        }
      },
      {
        "id": 192,
        "name": "Power-Off_Retract_Count",
        "value": 100,
        "worst": 100,
        "thresh": 0,
        "when_failed": "",
        "flags": {
          "value": 50,
          "string": "-O--CK ",
          "prefailure": false,
          "updated_online": true,
          "performance": false,
          "error_rate": false,
          "event_count": true,
          "auto_keep": true
        },
        "raw": {
          "value": 4,
          "string": "4"
        }
      },
      {
        "id": 193,
        "name": "Load_Cycle_Count",
        "value": 65,
        "worst": 65,
        "thresh": 0,
        "when_failed": "",
        "flags": {
          "value": 50,
          "string": "-O--CK ",
          "prefailure": false,
          "updated_online": true,
          "performance": false,
          "error_rate": false,
          "event_count": true,
          "auto_keep": true
        },
        "raw": {
          "value": 71560,
          "string": "71560"
        }
      },
      {
        "id": 194,
        "name": "Temperature_Celsius",
        "value": 37,
        "worst": 48,
        "thresh": 0,
        "when_failed": "",
        "flags": {
          "value": 34,
          "string": "-O---K ",
          "prefailure": false,
          "updated_online": true,
          "performance": false,
          "error_rate": false,
          "event_count": false,
          "auto_keep": true
        },
        "raw": {
          "value": 81604378661,
          "string": "37 (0 19 0 0 0)"
        }
      },
      {
        "id": 197,
        "name": "Current_Pending_Sector",
        "value": 90,
        "worst": 90,
        "thresh": 0,
        "when_failed": "",
        "flags": {
          "value": 18,
          "string": "-O--C- ",
          "prefailure": false,
          "updated_online": true,
          "performance": false,
          "error_rate": false,
          "event_count": true,
          "auto_keep": false
        },
        "raw": {
          "value": 1640,
          "string": "1640"
        }
      },
      {
        "id": 198,
        "name": "Offline_Uncorrectable",
        "value": 90,
        "worst": 90,
        "thresh": 0,
        "when_failed": "",
        "flags": {
          "value": 16,
          "string": "----C- ",
          "prefailure": false,
          "updated_online": false,
          "performance": false,
          "error_rate": false,
          "event_count": true,
          "auto_keep": false
        },
        "raw": {
          "value": 1640,
          "string": "1640"
        }
      },
      {
        "id": 199,
        "name": "UDMA_CRC_Error_Count",
        "value": 200,
        "worst": 200,
        "thresh": 0,
        "when_failed": "",
        "flags": {
          "value": 62,
          "string": "-OSRCK ",
          "prefailure": false,
          "updated_online": true,
          "performance": true,
          "error_rate": true,
          "event_count": true,
          "auto_keep": true
        },
        "raw": {
          "value": 0,
          "string": "0"
        }
      },
      {
        "id": 240,
        "name": "Head_Flying_Hours",
        "value": 100,
        "worst": 253,
        "thresh": 0,
        "when_failed": "",
        "flags": {
          "value": 0,
          "string": "------ ",
          "prefailure": false,
          "updated_online": false,
          "performance": false,
          "error_rate": false,
          "event_count": false,
          "auto_keep": false
        },
        "raw": {
          "value": 5335285684526225,
          "string": "23697h+20m+42.218s"
        }
      },
      {
        "id": 241,
        "name": "Total_LBAs_Written",
        "value": 100,
        "worst": 253,
        "thresh": 0,
        "when_failed": "",
        "flags": {
          "value": 0,
          "string": "------ ",
          "prefailure": false,
          "updated_online": false,
          "performance": false,
          "error_rate": false,
          "event_count": false,
          "auto_keep": false
        },
        "raw": {
          "value": 79823133273,
          "string": "79823133273"
        }
      },
      {
        "id": 242,
        "name": "Total_LBAs_Read",
        "value": 100,
        "worst": 253,
        "thresh": 0,
        "when_failed": "",
        "flags": {
          "value": 0,
          "string": "------ ",
          "prefailure": false,
          "updated_online": false,
          "performance": false,
          "error_rate": false,
          "event_count": false,
          "auto_keep": false
        },
        "raw": {
          "value": 11747615343661,
          "string": "11747615343661"
        }
      }
    ]
  },
  "power_on_time": {
    "hours": 27205
  },
  "power_cycle_count": 405,
  "temperature": {
    "current": 37
  },
  "ata_smart_error_log": {
    "summary": {
      "revision": 1,
      "count": 89,
      "logged_count": 5,
      "table": [
        {
          "error_number": 89,
          "lifetime_hours": 27191,
          "completion_registers": {
            "error": 64,
            "status": 83,
            "count": 0,
            "lba": 16777215,
            "device": 15
          },
          "error_description": "Error: UNC at LBA = 0x0fffffff = 268435455",
          "previous_commands": [
            {
              "registers": {
                "command": 96,
                "features": 0,
                "count": 0,
                "lba": 16777215,
                "device": 79,
                "device_control": 0
              },
              "powerup_milliseconds": 15296788,
              "command_name": "READ FPDMA QUEUED"
            },
            {
              "registers": {
                "command": 96,
                "features": 0,
                "count": 0,
                "lba": 16777215,
                "device": 79,
                "device_control": 0
              },
              "powerup_milliseconds": 15296788,
              "command_name": "READ FPDMA QUEUED"
            },
            {
              "registers": {
                "command": 239,
                "features": 16,
                "count": 2,
                "lba": 0,
                "device": 160,
                "device_control": 0
              },
              "powerup_milliseconds": 15296782,
              "command_name": "SET FEATURES [Enable SATA feature]"
            },
            {
              "registers": {
                "command": 39,
                "features": 0,
                "count": 0,
                "lba": 0,
                "device": 224,
                "device_control": 0
              },
              "powerup_milliseconds": 15296782,
              "command_name": "READ NATIVE MAX ADDRESS EXT [OBS-ACS-3]"
            },
            {
              "registers": {
                "command": 236,
                "features": 0,
                "count": 0,
                "lba": 0,
                "device": 160,
                "device_control": 0
              },
              "powerup_milliseconds": 15296782,
              "command_name": "IDENTIFY DEVICE"
            }
          ]
        },
        {
          "error_number": 88,
          "lifetime_hours": 27191,
          "completion_registers": {
            "error": 64,
            "status": 83,
            "count": 0,
            "lba": 16777215,
            "device": 15
          },
          "error_description": "Error: UNC at LBA = 0x0fffffff = 268435455",
          "previous_commands": [
            {
              "registers": {
                "command": 96,
                "features": 0,
                "count": 0,
                "lba": 16777215,
                "device": 79,
                "device_control": 0
              },
              "powerup_milliseconds": 15293051,
              "command_name": "READ FPDMA QUEUED"
            },
            {
              "registers": {
                "command": 96,
                "features": 0,
                "count": 0,
                "lba": 16777215,
                "device": 79,
                "device_control": 0
              },
              "powerup_milliseconds": 15293051,
              "command_name": "READ FPDMA QUEUED"
            },
            {
              "registers": {
                "command": 96,
                "features": 0,
                "count": 0,
                "lba": 16777215,
                "device": 79,
                "device_control": 0
              },
              "powerup_milliseconds": 15293051,
              "command_name": "READ FPDMA QUEUED"
            },
            {
              "registers": {
                "command": 96,
                "features": 0,
                "count": 0,
                "lba": 16777215,
                "device": 79,
                "device_control": 0
              },
              "powerup_milliseconds": 15293051,
              "command_name": "READ FPDMA QUEUED"
            },
            {
              "registers": {
                "command": 96,
                "features": 0,
                "count": 0,
                "lba": 16777215,
                "device": 79,
                "device_control": 0
              },
              "powerup_milliseconds": 15293037,
              "command_name": "READ FPDMA QUEUED"
            }
          ]
        },
        {
          "error_number": 87,
          "lifetime_hours": 27191,
          "completion_registers": {
            "error": 64,
            "status": 83,
            "count": 0,
            "lba": 16777215,
            "device": 15
          },
          "error_description": "Error: UNC at LBA = 0x0fffffff = 268435455",
          "previous_commands": [
            {
              "registers": {
                "command": 96,
                "features": 0,
                "count": 0,
                "lba": 16777215,
                "device": 79,
                "device_control": 0
              },
              "powerup_milliseconds": 15289285,
              "command_name": "READ FPDMA QUEUED"
            },
            {
              "registers": {
                "command": 96,
                "features": 0,
                "count": 0,
                "lba": 16777215,
                "device": 79,
                "device_control": 0
              },
              "powerup_milliseconds": 15289285,
              "command_name": "READ FPDMA QUEUED"
            },
            {
              "registers": {
                "command": 96,
                "features": 0,
                "count": 0,
                "lba": 16777215,
                "device": 79,
                "device_control": 0
              },
              "powerup_milliseconds": 15289285,
              "command_name": "READ FPDMA QUEUED"
            },
            {
              "registers": {
                "command": 96,
                "features": 0,
                "count": 0,
                "lba": 16777215,
                "device": 79,
                "device_control": 0
              },
              "powerup_milliseconds": 15289285,
              "command_name": "READ FPDMA QUEUED"
            },
            {
              "registers": {
                "command": 96,
                "features": 0,
                "count": 0,
                "lba": 16777215,
                "device": 79,
                "device_control": 0
              },
              "powerup_milliseconds": 15289265,
              "command_name": "READ FPDMA QUEUED"
            }
          ]
        },
        {
          "error_number": 86,
          "lifetime_hours": 27191,
          "completion_registers": {
            "error": 64,
            "status": 83,
            "count": 0,
            "lba": 16777215,
            "device": 15
          },
          "error_description": "Error: UNC at LBA = 0x0fffffff = 268435455",
          "previous_commands": [
            {
              "registers": {
                "command": 96,
                "features": 0,
                "count": 0,
                "lba": 16777215,
                "device": 79,
                "device_control": 0
              },
              "powerup_milliseconds": 15285545,
              "command_name": "READ FPDMA QUEUED"
            },
            {
              "registers": {
                "command": 96,
                "features": 0,
                "count": 0,
                "lba": 16777215,
                "device": 79,
                "device_control": 0
              },
              "powerup_milliseconds": 15285544,
              "command_name": "READ FPDMA QUEUED"
            },
            {
              "registers": {
                "command": 239,
                "features": 16,
                "count": 2,
                "lba": 0,
                "device": 160,
                "device_control": 0
              },
              "powerup_milliseconds": 15285539,
              "command_name": "SET FEATURES [Enable SATA feature]"
            },
            {
              "registers": {
                "command": 39,
                "features": 0,
                "count": 0,
                "lba": 0,
                "device": 224,
                "device_control": 0
              },
              "powerup_milliseconds": 15285539,
              "command_name": "READ NATIVE MAX ADDRESS EXT [OBS-ACS-3]"
            },
            {
              "registers": {
                "command": 236,
                "features": 0,
                "count": 0,
                "lba": 0,
                "device": 160,
                "device_control": 0
              },
              "powerup_milliseconds": 15285538,
              "command_name": "IDENTIFY DEVICE"
            }
          ]
        },
        {
          "error_number": 85,
          "lifetime_hours": 27191,
          "completion_registers": {
            "error": 64,
            "status": 83,
            "count": 0,
            "lba": 16777215,
            "device": 15
          },
          "error_description": "Error: UNC at LBA = 0x0fffffff = 268435455",
          "previous_commands": [
            {
              "registers": {
                "command": 96,
                "features": 0,
                "count": 0,
                "lba": 16777215,
                "device": 79,
                "device_control": 0
              },
              "powerup_milliseconds": 15282058,
              "command_name": "READ FPDMA QUEUED"
            },
            {
              "registers": {
                "command": 96,
                "features": 0,
                "count": 0,
                "lba": 16777215,
                "device": 79,
                "device_control": 0
              },
              "powerup_milliseconds": 15282058,
              "command_name": "READ FPDMA QUEUED"
            },
            {
              "registers": {
                "command": 96,
                "features": 0,
                "count": 0,
                "lba": 16777215,
                "device": 79,
                "device_control": 0
              },
              "powerup_milliseconds": 15281380,
              "command_name": "READ FPDMA QUEUED"
            },
            {
              "registers": {
                "command": 96,
                "features": 0,
                "count": 0,
                "lba": 16777215,
                "device": 79,
                "device_control": 0
              },
              "powerup_milliseconds": 15281380,
              "command_name": "READ FPDMA QUEUED"
            },
            {
              "registers": {
                "command": 96,
                "features": 0,
                "count": 0,
                "lba": 16777215,
                "device": 79,
                "device_control": 0
              },
              "powerup_milliseconds": 15281380,
              "command_name": "READ FPDMA QUEUED"
            }
          ]
        }
      ]
    }
  },
  "ata_smart_self_test_log": {
    "standard": {
      "revision": 1,
      "table": [
        {
          "type": {
            "value": 1,
            "string": "Short offline"
          },
          "status": {
            "value": 121,
            "string": "Completed: read failure",
            "remaining_percent": 90,
            "passed": false
          },
          "lifetime_hours": 27200,
          "lba": 4132075584
        },
        {
          "type": {
            "value": 2,
            "string": "Extended offline"
          },
          "status": {
            "value": 121,
            "string": "Completed: read failure",
            "remaining_percent": 90,
            "passed": false
          },
          "lifetime_hours": 27196,
          "lba": 4132075584
        },
        {
          "type": {
            "value": 2,
            "string": "Extended offline"
          },
          "status": {
            "value": 121,
            "string": "Completed: read failure",
            "remaining_percent": 90,
            "passed": false
          },
          "lifetime_hours": 27184,
          "lba": 4097844144
        },
        {
          "type": {
            "value": 2,
            "string": "Extended offline"
          },
          "status": {
            "value": 121,
            "string": "Completed: read failure",
            "remaining_percent": 90,
            "passed": false
          },
          "lifetime_hours": 27182,
          "lba": 4097844144
        },
        {
          "type": {
            "value": 2,
            "string": "Extended offline"
          },
          "status": {
            "value": 121,
            "string": "Completed: read failure",
            "remaining_percent": 90,
            "passed": false
          },
          "lifetime_hours": 27182,
          "lba": 4097844144
        },
        {
          "type": {
            "value": 1,
            "string": "Short offline"
          },
          "status": {
            "value": 121,
            "string": "Completed: read failure",
            "remaining_percent": 90,
            "passed": false
          },
          "lifetime_hours": 27176,
          "lba": 4097844144
        },
        {
          "type": {
            "value": 1,
            "string": "Short offline"
          },
          "status": {
            "value": 121,
            "string": "Completed: read failure",
            "remaining_percent": 90,
            "passed": false
          },
          "lifetime_hours": 27153,
          "lba": 4097844144
        },
        {
          "type": {
            "value": 1,
            "string": "Short offline"
          },
          "status": {
            "value": 0,
            "string": "Completed without error",
            "passed": true
          },
          "lifetime_hours": 27129
        },
        {
          "type": {
            "value": 1,
            "string": "Short offline"
          },
          "status": {
            "value": 0,
            "string": "Completed without error",
            "passed": true
          },
          "lifetime_hours": 27105
        },
        {
          "type": {
            "value": 1,
            "string": "Short offline"
          },
          "status": {
            "value": 0,
            "string": "Completed without error",
            "passed": true
          },
          "lifetime_hours": 27081
        },
        {
          "type": {
            "value": 1,
            "string": "Short offline"
          },
          "status": {
            "value": 0,
            "string": "Completed without error",
            "passed": true
          },
          "lifetime_hours": 27062
        },
        {
          "type": {
            "value": 1,
            "string": "Short offline"
          },
          "status": {
            "value": 0,
            "string": "Completed without error",
            "passed": true
          },
          "lifetime_hours": 27038
        },
        {
          "type": {
            "value": 1,
            "string": "Short offline"
          },
          "status": {
            "value": 0,
            "string": "Completed without error",
            "passed": true
          },
          "lifetime_hours": 27014
        },
        {
          "type": {
            "value": 1,
            "string": "Short offline"
          },
          "status": {
            "value": 0,
            "string": "Completed without error",
            "passed": true
          },
          "lifetime_hours": 26990
        },
        {
          "type": {
            "value": 1,
            "string": "Short offline"
          },
          "status": {
            "value": 0,
            "string": "Completed without error",
            "passed": true
          },
          "lifetime_hours": 26966
        },
        {
          "type": {
            "value": 1,
            "string": "Short offline"
          },
          "status": {
            "value": 0,
            "string": "Completed without error",
            "passed": true
          },
          "lifetime_hours": 26942
        },
        {
          "type": {
            "value": 1,
            "string": "Short offline"
          },
          "status": {
            "value": 0,
            "string": "Completed without error",
            "passed": true
          },
          "lifetime_hours": 26918
        },
        {
          "type": {
            "value": 1,
            "string": "Short offline"
          },
          "status": {
            "value": 0,
            "string": "Completed without error",
            "passed": true
          },
          "lifetime_hours": 26894
        },
        {
          "type": {
            "value": 1,
            "string": "Short offline"
          },
          "status": {
            "value": 0,
            "string": "Completed without error",
            "passed": true
          },
          "lifetime_hours": 26870
        },
        {
          "type": {
            "value": 1,
            "string": "Short offline"
          },
          "status": {
            "value": 0,
            "string": "Completed without error",
            "passed": true
          },
          "lifetime_hours": 26846
        },
        {
          "type": {
            "value": 1,
            "string": "Short offline"
          },
          "status": {
            "value": 0,
            "string": "Completed without error",
            "passed": true
          },
          "lifetime_hours": 26822
        }
      ],
      "count": 21,
      "error_count_total": 7,
      "error_count_outdated": 0
    }
  },
  "ata_smart_selective_self_test_log": {
    "revision": 1,
    "table": [
      {
        "lba_min": 0,
        "lba_max": 0,
        "status": {
          "value": 0,
          "string": "Not_testing"
        }
      },
      {
        "lba_min": 0,
        "lba_max": 0,
        "status": {
          "value": 0,
          "string": "Not_testing"
        }
      },
      {
        "lba_min": 0,
        "lba_max": 0,
        "status": {
          "value": 0,
          "string": "Not_testing"
        }
      },
      {
        "lba_min": 0,
        "lba_max": 0,
        "status": {
          "value": 0,
          "string": "Not_testing"
        }
      },
      {
        "lba_min": 0,
        "lba_max": 0,
        "status": {
          "value": 0,
          "string": "Not_testing"
        }
      }
    ],
    "flags": {
      "value": 0,
      "remainder_scan_enabled": false
    },
    "power_up_scan_resume_minutes": 0
  }
}

